health/__init__.py
health/classes/__init__.py
health/classes/activity_summary.py
health/classes/base.py
health/classes/correlation.py
health/classes/me.py
health/classes/record.py
health/classes/workout.py
health/constants/__init__.py
health/constants/correlation.py
health/constants/me.py
health/constants/metadata.py
health/constants/record.py
health/constants/workout.py
health/data.py
health/util.py
apple_health-2.0.0.dist-info/LICENSE
apple_health-2.0.0.dist-info/WHEEL
apple_health-2.0.0.dist-info/METADATA
apple_health-2.0.0.dist-info/RECORD
