Metadata-Version: 2.1
Name: apple-health
Version: 2.0.0
Summary: Library to extract information from Apple Health exports.
Home-page: https://github.com/fedecalendino/apple-health
License: MIT
Keywords: parser,apple health
Author: Fede Calendino
Author-email: fede@calendino.com
Requires-Python: >=3.8,<4.0
Classifier: Intended Audience :: Developers
Classifier: License :: OSI Approved :: MIT License
Classifier: Programming Language :: Python :: 3
Classifier: Programming Language :: Python :: 3.10
Classifier: Programming Language :: Python :: 3.8
Classifier: Programming Language :: Python :: 3.9
Requires-Dist: python-dateutil (>=2.8.2,<3.0.0)
Requires-Dist: xmltodict (>=0.13.0,<0.14.0)
Project-URL: Documentation, https://github.com/fedecalendino/apple-health/blob/main/README.md
